p1read/__init__.py
p1read/__main__.py
p1read/p1.py
p1read-1.0.8.dist-info/METADATA
p1read-1.0.8.dist-info/WHEEL
p1read-1.0.8.dist-info/entry_points.txt
p1read-1.0.8.dist-info/top_level.txt
p1read-1.0.8.dist-info/RECORD
